graphepp/__init__.py
graphepp/graphepp.py
graphepp/version.py
graphepp-0.5.dist-info/LICENSE
graphepp-0.5.dist-info/METADATA
graphepp-0.5.dist-info/WHEEL
graphepp-0.5.dist-info/top_level.txt
graphepp-0.5.dist-info/RECORD
