Metadata-Version: 2.1
Name: graphepp
Version: 0.5
Summary: A collection of functions for multipartite entanglement purification protocols (EPP) on noisy graph states
Author: Julius Wallnöfer
License: MIT License
Project-URL: homepage, https://github.com/jwallnoefer/graphepp
Keywords: quantum information,quantum information theory,graph,graph state,entanglement,entanglement purification,entanglement purification protocol,EPP,entanglement distillation,multipartite entanglement
Classifier: License :: OSI Approved :: MIT License
Classifier: Programming Language :: Python :: 3
Classifier: Topic :: Scientific/Engineering :: Physics
Classifier: Intended Audience :: Science/Research
Requires-Python: >=3.8.5
License-File: LICENSE
Requires-Dist: numpy >=1.19.2
Provides-Extra: docs
Requires-Dist: sphinx ; extra == 'docs'
Requires-Dist: autodocsumm ; extra == 'docs'
Requires-Dist: recommonmark ==0.7.1 ; extra == 'docs'
Requires-Dist: sphinx-rtd-theme ; extra == 'docs'
Provides-Extra: test
Requires-Dist: pytest ; extra == 'test'
